skillfluxutils/__init__.py
skillfluxutils/parser.py
skillfluxutils-0.1.0.dist-info/licenses/LICENSE
skillfluxutils-0.1.0.dist-info/METADATA
skillfluxutils-0.1.0.dist-info/WHEEL
skillfluxutils-0.1.0.dist-info/top_level.txt
skillfluxutils-0.1.0.dist-info/RECORD
